{
  "minecraft:recipes/redstone/oak_fence_gate": {
    "criteria": {
      "has_planks": "2023-03-19 23:39:13 -0400"
    },
    "done": true
  },
  "minecraft:recipes/tools/clock": {
    "criteria": {
      "has_redstone": "2023-03-19 23:39:46 -0400"
    },
    "done": true
  },
  "minecraft:recipes/transportation/dark_oak_boat": {
    "criteria": {
      "in_water": "2023-03-19 23:40:12 -0400"
    },
    "done": true
  },
  "minecraft:recipes/tools/compass": {
    "criteria": {
      "has_redstone": "2023-03-19 23:39:46 -0400"
    },
    "done": true
  },
  "minecraft:recipes/redstone/oak_button": {
    "criteria": {
      "has_planks": "2023-03-19 23:39:13 -0400"
    },
    "done": true
  },
  "minecraft:recipes/redstone/redstone_block": {
    "criteria": {
      "has_redstone": "2023-03-19 23:39:46 -0400"
    },
    "done": true
  },
  "create:recipes/create.base/crafting/logistics/powered_latch": {
    "criteria": {
      "has_item": "2023-03-19 23:39:46 -0400"
    },
    "done": true
  },
  "minecraft:recipes/redstone/piston": {
    "criteria": {
      "has_redstone": "2023-03-19 23:39:46 -0400"
    },
    "done": true
  },
  "minecraft:recipes/redstone/target": {
    "criteria": {
      "has_redstone": "2023-03-19 23:39:46 -0400"
    },
    "done": true
  },
  "create:recipes/create.base/crafting/logistics/pulse_repeater": {
    "criteria": {
      "has_item": "2023-03-19 23:39:46 -0400"
    },
    "done": true
  },
  "create:recipes/create.base/crafting/logistics/pulse_extender": {
    "criteria": {
      "has_item": "2023-03-19 23:39:46 -0400"
    },
    "done": true
  },
  "minecraft:recipes/redstone/oak_pressure_plate": {
    "criteria": {
      "has_planks": "2023-03-19 23:39:13 -0400"
    },
    "done": true
  },
  "minecraft:adventure/adventuring_time": {
    "criteria": {
      "minecraft:beach": "2023-03-19 23:39:01 -0400",
      "minecraft:ocean": "2023-03-19 23:40:12 -0400"
    },
    "done": false
  },
  "minecraft:recipes/decorations/crafting_table": {
    "criteria": {
      "has_planks": "2023-03-19 23:39:13 -0400"
    },
    "done": true
  },
  "create:recipes/create.base/crafting/materials/rose_quartz": {
    "criteria": {
      "has_item": "2023-03-19 23:39:46 -0400"
    },
    "done": true
  },
  "computercraft:recipes/computercraft/computer_normal": {
    "criteria": {
      "has_redstone": "2023-03-19 23:39:46 -0400"
    },
    "done": true
  },
  "create:root": {
    "criteria": {
      "0": "2023-03-19 23:39:11 -0400"
    },
    "done": true
  },
  "create:recipes/create.base/crafting/logistics/powered_toggle_latch": {
    "criteria": {
      "has_item": "2023-03-19 23:39:46 -0400"
    },
    "done": true
  },
  "minecraft:recipes/redstone/redstone_torch": {
    "criteria": {
      "has_redstone": "2023-03-19 23:39:46 -0400"
    },
    "done": true
  },
  "minecraft:recipes/transportation/birch_boat": {
    "criteria": {
      "in_water": "2023-03-19 23:40:12 -0400"
    },
    "done": true
  },
  "minecraft:recipes/redstone/note_block": {
    "criteria": {
      "has_redstone": "2023-03-19 23:39:46 -0400"
    },
    "done": true
  },
  "minecraft:recipes/building_blocks/oak_stairs": {
    "criteria": {
      "has_planks": "2023-03-19 23:39:13 -0400"
    },
    "done": true
  },
  "minecraft:recipes/decorations/barrel": {
    "criteria": {
      "has_planks": "2023-03-19 23:39:13 -0400"
    },
    "done": true
  },
  "minecraft:recipes/decorations/oak_fence": {
    "criteria": {
      "has_planks": "2023-03-19 23:39:13 -0400"
    },
    "done": true
  },
  "minecraft:recipes/transportation/acacia_boat": {
    "criteria": {
      "in_water": "2023-03-19 23:40:12 -0400"
    },
    "done": true
  },
  "minecraft:recipes/transportation/oak_boat": {
    "criteria": {
      "in_water": "2023-03-19 23:40:12 -0400"
    },
    "done": true
  },
  "minecraft:recipes/redstone/dropper": {
    "criteria": {
      "has_redstone": "2023-03-19 23:39:46 -0400"
    },
    "done": true
  },
  "minecraft:recipes/redstone/oak_door": {
    "criteria": {
      "has_planks": "2023-03-19 23:39:13 -0400"
    },
    "done": true
  },
  "minecraft:recipes/decorations/oak_sign": {
    "criteria": {
      "has_planks": "2023-03-19 23:39:13 -0400"
    },
    "done": true
  },
  "minecraft:recipes/misc/stick": {
    "criteria": {
      "has_planks": "2023-03-19 23:39:13 -0400"
    },
    "done": true
  },
  "minecraft:recipes/redstone/oak_trapdoor": {
    "criteria": {
      "has_planks": "2023-03-19 23:39:13 -0400"
    },
    "done": true
  },
  "minecraft:recipes/building_blocks/oak_slab": {
    "criteria": {
      "has_planks": "2023-03-19 23:39:13 -0400"
    },
    "done": true
  },
  "minecraft:recipes/transportation/jungle_boat": {
    "criteria": {
      "in_water": "2023-03-19 23:40:12 -0400"
    },
    "done": true
  },
  "minecraft:recipes/transportation/spruce_boat": {
    "criteria": {
      "in_water": "2023-03-19 23:40:12 -0400"
    },
    "done": true
  },
  "create:recipes/create.palettes/oak_window": {
    "criteria": {
      "has_ingredient": "2023-03-19 23:39:13 -0400"
    },
    "done": true
  },
  "minecraft:recipes/misc/netherite_ingot_from_netherite_block": {
    "criteria": {
      "has_netherite_block": "2023-03-19 23:39:35 -0400"
    },
    "done": true
  },
  "DataVersion": 2975
}